p2f_hydrates/KlaudaSandlerLangParams.csv
p2f_hydrates/KlaudaSandlerP_vap.csv
p2f_hydrates/Organic Inhibitor Data.csv
p2f_hydrates/Salt Data.csv
p2f_hydrates/__init__.py
p2f_hydrates/componentData.csv
p2f_hydrates/core.py
p2f_hydrates/hydrateCellProperties.csv
p2f_hydrates/interactionParameters.csv
p2f_hydrates/model.py
p2f_hydrates-0.1.0.1.dist-info/METADATA
p2f_hydrates-0.1.0.1.dist-info/WHEEL
p2f_hydrates-0.1.0.1.dist-info/RECORD
