Metadata-Version: 2.4
Name: p2f_hydrates
Version: 0.1.0.1
Summary: A package providing functionality for the simulation of equilibrium and inhibition of clathrate hydrates
Project-URL: Homepage, https://github.com/karstenkunneman/p2f_hydrates
Project-URL: Issues, https://github.com/karstenkunneman/p2f_hydrates/issues
Author-email: Karsten Kunneman <karstenkunneman@protonmail.com>, "Amadeu K. Sum" <asum@mines.edu>
License-Expression: CC-BY-SA-4.0
Classifier: Operating System :: OS Independent
Classifier: Programming Language :: Python :: 3
Requires-Python: >=3.8
Requires-Dist: matplotlib==3.7.5
Requires-Dist: numpy==1.21.0
Requires-Dist: thermo==0.4.1
